captcha_admin/__init__.py
captcha_admin/admin.py
captcha_admin/forms.py
captcha_admin/settings.py
captcha_admin/templates/admin/login.html
django_grappelli_captcha_admin-1.0.0.dist-info/LICENSE
django_grappelli_captcha_admin-1.0.0.dist-info/METADATA
django_grappelli_captcha_admin-1.0.0.dist-info/WHEEL
django_grappelli_captcha_admin-1.0.0.dist-info/top_level.txt
django_grappelli_captcha_admin-1.0.0.dist-info/RECORD
