Metadata-Version: 2.1
Name: django-grappelli-captcha-admin
Version: 1.0.0
Summary: easy added captcha to login page of django grappelli admin
Home-page: http://github.com/xcai/django-grappelli-captcha-admin
Download-URL: https://pypi.python.org/pypi/django-grappelli-captcha-admin/
Author: xcai
Author-email: xxiaocai@163.com
License: MIT
Keywords: django captcha recaptcha recaptcha2 simple-captcha admin grappelli
Platform: any
Classifier: Environment :: Web Environment
Classifier: Framework :: Django
Classifier: Intended Audience :: Developers
Classifier: Operating System :: OS Independent
Classifier: Programming Language :: Python
Classifier: Topic :: Software Development :: Libraries :: Application Frameworks
Classifier: Topic :: Software Development :: Libraries :: Python Modules
Requires-Python: >=3
License-File: LICENSE
Requires-Dist: django
Requires-Dist: django-grappelli
